{
    "items": [
        {
            "title": "Article 1",
            "content": "<p>Lorem ipsum dolor sit amet, consectetur adipiscing elit. Pellentesque vestibulum tempus scelerisque. Morbi diam arcu, suscipit molestie rhoncus in, varius quis turpis. Quisque a risus eget leo cursus adipiscing in eu odio. Nullam id arcu mauris. In ullamcorper est et tortor vestibulum vitae rhoncus erat dignissim. Vestibulum dolor lorem, commodo ac sollicitudin sit amet, fermentum nec justo. Maecenas vitae interdum ipsum. Nulla facilisi. Ut eget nunc sed turpis sollicitudin varius tincidunt vel turpis. Sed blandit, sapien eu vehicula aliquam, metus neque rutrum massa, id vehicula elit lorem in sapien. Vestibulum a massa in sem posuere suscipit. Vivamus eget enim quis tellus mattis vehicula. Pellentesque rhoncus, massa in pellentesque scelerisque, mauris diam ultricies justo, vel vulputate metus lacus quis nibh. Mauris ut viverra sem.</p><p>Vivamus consectetur fringilla magna sed iaculis. Duis eros tortor, varius in tincidunt nec, ullamcorper non dolor. Suspendisse a turpis in sem laoreet molestie. Pellentesque consectetur suscipit dictum. Nam vehicula turpis nec massa laoreet rhoncus. Pellentesque in arcu orci. Aenean eget nulla metus. Sed magna massa, congue non rhoncus vitae, condimentum vitae nisi. Pellentesque a lectus nunc, quis elementum elit. Aliquam erat volutpat. Aliquam tincidunt sem quis elit blandit blandit. Nunc ultrices risus quis eros accumsan id luctus metus faucibus. Donec eu erat tortor, quis sagittis orci. Maecenas hendrerit enim id est pellentesque pulvinar. Aenean vulputate dapibus nibh vel sagittis.</p><p>In interdum magna ut mauris ultricies a dignissim massa feugiat. Suspendisse id lectus sit amet mi rhoncus tempor. Maecenas et facilisis metus. Suspendisse lorem neque, varius id dignissim a, egestas eget erat. Nulla congue volutpat eleifend. Quisque fringilla euismod mi, id malesuada augue rhoncus ut. Quisque viverra pharetra arcu, eget accumsan arcu adipiscing ut. Cras ultrices elit scelerisque augue imperdiet consectetur. Phasellus faucibus scelerisque pharetra.</p>"
        },
        {
            "title": "Article 2",
            "content": "<p>Lorem ipsum dolor sit amet, consectetur adipiscing elit. Pellentesque vestibulum tempus scelerisque. Morbi diam arcu, suscipit molestie rhoncus in, varius quis turpis. Quisque a risus eget leo cursus adipiscing in eu odio. Nullam id arcu mauris. In ullamcorper est et tortor vestibulum vitae rhoncus erat dignissim. Vestibulum dolor lorem, commodo ac sollicitudin sit amet, fermentum nec justo. Maecenas vitae interdum ipsum. Nulla facilisi. Ut eget nunc sed turpis sollicitudin varius tincidunt vel turpis. Sed blandit, sapien eu vehicula aliquam, metus neque rutrum massa, id vehicula elit lorem in sapien. Vestibulum a massa in sem posuere suscipit. Vivamus eget enim quis tellus mattis vehicula. Pellentesque rhoncus, massa in pellentesque scelerisque, mauris diam ultricies justo, vel vulputate metus lacus quis nibh. Mauris ut viverra sem.</p><p>Vivamus consectetur fringilla magna sed iaculis. Duis eros tortor, varius in tincidunt nec, ullamcorper non dolor. Suspendisse a turpis in sem laoreet molestie. Pellentesque consectetur suscipit dictum. Nam vehicula turpis nec massa laoreet rhoncus. Pellentesque in arcu orci. Aenean eget nulla metus. Sed magna massa, congue non rhoncus vitae, condimentum vitae nisi. Pellentesque a lectus nunc, quis elementum elit. Aliquam erat volutpat. Aliquam tincidunt sem quis elit blandit blandit. Nunc ultrices risus quis eros accumsan id luctus metus faucibus. Donec eu erat tortor, quis sagittis orci. Maecenas hendrerit enim id est pellentesque pulvinar. Aenean vulputate dapibus nibh vel sagittis.</p><p>In interdum magna ut mauris ultricies a dignissim massa feugiat. Suspendisse id lectus sit amet mi rhoncus tempor. Maecenas et facilisis metus. Suspendisse lorem neque, varius id dignissim a, egestas eget erat. Nulla congue volutpat eleifend. Quisque fringilla euismod mi, id malesuada augue rhoncus ut. Quisque viverra pharetra arcu, eget accumsan arcu adipiscing ut. Cras ultrices elit scelerisque augue imperdiet consectetur. Phasellus faucibus scelerisque pharetra.</p>"
        },
        {
            "title": "Article 3",
            "content": "<p>Lorem ipsum dolor sit amet, consectetur adipiscing elit. Pellentesque vestibulum tempus scelerisque. Morbi diam arcu, suscipit molestie rhoncus in, varius quis turpis. Quisque a risus eget leo cursus adipiscing in eu odio. Nullam id arcu mauris. In ullamcorper est et tortor vestibulum vitae rhoncus erat dignissim. Vestibulum dolor lorem, commodo ac sollicitudin sit amet, fermentum nec justo. Maecenas vitae interdum ipsum. Nulla facilisi. Ut eget nunc sed turpis sollicitudin varius tincidunt vel turpis. Sed blandit, sapien eu vehicula aliquam, metus neque rutrum massa, id vehicula elit lorem in sapien. Vestibulum a massa in sem posuere suscipit. Vivamus eget enim quis tellus mattis vehicula. Pellentesque rhoncus, massa in pellentesque scelerisque, mauris diam ultricies justo, vel vulputate metus lacus quis nibh. Mauris ut viverra sem.</p><p>Vivamus consectetur fringilla magna sed iaculis. Duis eros tortor, varius in tincidunt nec, ullamcorper non dolor. Suspendisse a turpis in sem laoreet molestie. Pellentesque consectetur suscipit dictum. Nam vehicula turpis nec massa laoreet rhoncus. Pellentesque in arcu orci. Aenean eget nulla metus. Sed magna massa, congue non rhoncus vitae, condimentum vitae nisi. Pellentesque a lectus nunc, quis elementum elit. Aliquam erat volutpat. Aliquam tincidunt sem quis elit blandit blandit. Nunc ultrices risus quis eros accumsan id luctus metus faucibus. Donec eu erat tortor, quis sagittis orci. Maecenas hendrerit enim id est pellentesque pulvinar. Aenean vulputate dapibus nibh vel sagittis.</p><p>In interdum magna ut mauris ultricies a dignissim massa feugiat. Suspendisse id lectus sit amet mi rhoncus tempor. Maecenas et facilisis metus. Suspendisse lorem neque, varius id dignissim a, egestas eget erat. Nulla congue volutpat eleifend. Quisque fringilla euismod mi, id malesuada augue rhoncus ut. Quisque viverra pharetra arcu, eget accumsan arcu adipiscing ut. Cras ultrices elit scelerisque augue imperdiet consectetur. Phasellus faucibus scelerisque pharetra.</p>"
        },
        {
            "title": "Article 4",
            "content": "<p>Lorem ipsum dolor sit amet, consectetur adipiscing elit. Pellentesque vestibulum tempus scelerisque. Morbi diam arcu, suscipit molestie rhoncus in, varius quis turpis. Quisque a risus eget leo cursus adipiscing in eu odio. Nullam id arcu mauris. In ullamcorper est et tortor vestibulum vitae rhoncus erat dignissim. Vestibulum dolor lorem, commodo ac sollicitudin sit amet, fermentum nec justo. Maecenas vitae interdum ipsum. Nulla facilisi. Ut eget nunc sed turpis sollicitudin varius tincidunt vel turpis. Sed blandit, sapien eu vehicula aliquam, metus neque rutrum massa, id vehicula elit lorem in sapien. Vestibulum a massa in sem posuere suscipit. Vivamus eget enim quis tellus mattis vehicula. Pellentesque rhoncus, massa in pellentesque scelerisque, mauris diam ultricies justo, vel vulputate metus lacus quis nibh. Mauris ut viverra sem.</p><p>Vivamus consectetur fringilla magna sed iaculis. Duis eros tortor, varius in tincidunt nec, ullamcorper non dolor. Suspendisse a turpis in sem laoreet molestie. Pellentesque consectetur suscipit dictum. Nam vehicula turpis nec massa laoreet rhoncus. Pellentesque in arcu orci. Aenean eget nulla metus. Sed magna massa, congue non rhoncus vitae, condimentum vitae nisi. Pellentesque a lectus nunc, quis elementum elit. Aliquam erat volutpat. Aliquam tincidunt sem quis elit blandit blandit. Nunc ultrices risus quis eros accumsan id luctus metus faucibus. Donec eu erat tortor, quis sagittis orci. Maecenas hendrerit enim id est pellentesque pulvinar. Aenean vulputate dapibus nibh vel sagittis.</p><p>In interdum magna ut mauris ultricies a dignissim massa feugiat. Suspendisse id lectus sit amet mi rhoncus tempor. Maecenas et facilisis metus. Suspendisse lorem neque, varius id dignissim a, egestas eget erat. Nulla congue volutpat eleifend. Quisque fringilla euismod mi, id malesuada augue rhoncus ut. Quisque viverra pharetra arcu, eget accumsan arcu adipiscing ut. Cras ultrices elit scelerisque augue imperdiet consectetur. Phasellus faucibus scelerisque pharetra.</p>"
        },
        {
            "title": "Article 5",
            "content": "<p>Lorem ipsum dolor sit amet, consectetur adipiscing elit. Pellentesque vestibulum tempus scelerisque. Morbi diam arcu, suscipit molestie rhoncus in, varius quis turpis. Quisque a risus eget leo cursus adipiscing in eu odio. Nullam id arcu mauris. In ullamcorper est et tortor vestibulum vitae rhoncus erat dignissim. Vestibulum dolor lorem, commodo ac sollicitudin sit amet, fermentum nec justo. Maecenas vitae interdum ipsum. Nulla facilisi. Ut eget nunc sed turpis sollicitudin varius tincidunt vel turpis. Sed blandit, sapien eu vehicula aliquam, metus neque rutrum massa, id vehicula elit lorem in sapien. Vestibulum a massa in sem posuere suscipit. Vivamus eget enim quis tellus mattis vehicula. Pellentesque rhoncus, massa in pellentesque scelerisque, mauris diam ultricies justo, vel vulputate metus lacus quis nibh. Mauris ut viverra sem.</p><p>Vivamus consectetur fringilla magna sed iaculis. Duis eros tortor, varius in tincidunt nec, ullamcorper non dolor. Suspendisse a turpis in sem laoreet molestie. Pellentesque consectetur suscipit dictum. Nam vehicula turpis nec massa laoreet rhoncus. Pellentesque in arcu orci. Aenean eget nulla metus. Sed magna massa, congue non rhoncus vitae, condimentum vitae nisi. Pellentesque a lectus nunc, quis elementum elit. Aliquam erat volutpat. Aliquam tincidunt sem quis elit blandit blandit. Nunc ultrices risus quis eros accumsan id luctus metus faucibus. Donec eu erat tortor, quis sagittis orci. Maecenas hendrerit enim id est pellentesque pulvinar. Aenean vulputate dapibus nibh vel sagittis.</p><p>In interdum magna ut mauris ultricies a dignissim massa feugiat. Suspendisse id lectus sit amet mi rhoncus tempor. Maecenas et facilisis metus. Suspendisse lorem neque, varius id dignissim a, egestas eget erat. Nulla congue volutpat eleifend. Quisque fringilla euismod mi, id malesuada augue rhoncus ut. Quisque viverra pharetra arcu, eget accumsan arcu adipiscing ut. Cras ultrices elit scelerisque augue imperdiet consectetur. Phasellus faucibus scelerisque pharetra.</p>"
        },
        {
            "title": "Article 6",
            "content": "<p>Lorem ipsum dolor sit amet, consectetur adipiscing elit. Pellentesque vestibulum tempus scelerisque. Morbi diam arcu, suscipit molestie rhoncus in, varius quis turpis. Quisque a risus eget leo cursus adipiscing in eu odio. Nullam id arcu mauris. In ullamcorper est et tortor vestibulum vitae rhoncus erat dignissim. Vestibulum dolor lorem, commodo ac sollicitudin sit amet, fermentum nec justo. Maecenas vitae interdum ipsum. Nulla facilisi. Ut eget nunc sed turpis sollicitudin varius tincidunt vel turpis. Sed blandit, sapien eu vehicula aliquam, metus neque rutrum massa, id vehicula elit lorem in sapien. Vestibulum a massa in sem posuere suscipit. Vivamus eget enim quis tellus mattis vehicula. Pellentesque rhoncus, massa in pellentesque scelerisque, mauris diam ultricies justo, vel vulputate metus lacus quis nibh. Mauris ut viverra sem.</p><p>Vivamus consectetur fringilla magna sed iaculis. Duis eros tortor, varius in tincidunt nec, ullamcorper non dolor. Suspendisse a turpis in sem laoreet molestie. Pellentesque consectetur suscipit dictum. Nam vehicula turpis nec massa laoreet rhoncus. Pellentesque in arcu orci. Aenean eget nulla metus. Sed magna massa, congue non rhoncus vitae, condimentum vitae nisi. Pellentesque a lectus nunc, quis elementum elit. Aliquam erat volutpat. Aliquam tincidunt sem quis elit blandit blandit. Nunc ultrices risus quis eros accumsan id luctus metus faucibus. Donec eu erat tortor, quis sagittis orci. Maecenas hendrerit enim id est pellentesque pulvinar. Aenean vulputate dapibus nibh vel sagittis.</p><p>In interdum magna ut mauris ultricies a dignissim massa feugiat. Suspendisse id lectus sit amet mi rhoncus tempor. Maecenas et facilisis metus. Suspendisse lorem neque, varius id dignissim a, egestas eget erat. Nulla congue volutpat eleifend. Quisque fringilla euismod mi, id malesuada augue rhoncus ut. Quisque viverra pharetra arcu, eget accumsan arcu adipiscing ut. Cras ultrices elit scelerisque augue imperdiet consectetur. Phasellus faucibus scelerisque pharetra.</p>"
        },
        {
            "title": "Article 7",
            "content": "<p>Lorem ipsum dolor sit amet, consectetur adipiscing elit. Pellentesque vestibulum tempus scelerisque. Morbi diam arcu, suscipit molestie rhoncus in, varius quis turpis. Quisque a risus eget leo cursus adipiscing in eu odio. Nullam id arcu mauris. In ullamcorper est et tortor vestibulum vitae rhoncus erat dignissim. Vestibulum dolor lorem, commodo ac sollicitudin sit amet, fermentum nec justo. Maecenas vitae interdum ipsum. Nulla facilisi. Ut eget nunc sed turpis sollicitudin varius tincidunt vel turpis. Sed blandit, sapien eu vehicula aliquam, metus neque rutrum massa, id vehicula elit lorem in sapien. Vestibulum a massa in sem posuere suscipit. Vivamus eget enim quis tellus mattis vehicula. Pellentesque rhoncus, massa in pellentesque scelerisque, mauris diam ultricies justo, vel vulputate metus lacus quis nibh. Mauris ut viverra sem.</p><p>Vivamus consectetur fringilla magna sed iaculis. Duis eros tortor, varius in tincidunt nec, ullamcorper non dolor. Suspendisse a turpis in sem laoreet molestie. Pellentesque consectetur suscipit dictum. Nam vehicula turpis nec massa laoreet rhoncus. Pellentesque in arcu orci. Aenean eget nulla metus. Sed magna massa, congue non rhoncus vitae, condimentum vitae nisi. Pellentesque a lectus nunc, quis elementum elit. Aliquam erat volutpat. Aliquam tincidunt sem quis elit blandit blandit. Nunc ultrices risus quis eros accumsan id luctus metus faucibus. Donec eu erat tortor, quis sagittis orci. Maecenas hendrerit enim id est pellentesque pulvinar. Aenean vulputate dapibus nibh vel sagittis.</p><p>In interdum magna ut mauris ultricies a dignissim massa feugiat. Suspendisse id lectus sit amet mi rhoncus tempor. Maecenas et facilisis metus. Suspendisse lorem neque, varius id dignissim a, egestas eget erat. Nulla congue volutpat eleifend. Quisque fringilla euismod mi, id malesuada augue rhoncus ut. Quisque viverra pharetra arcu, eget accumsan arcu adipiscing ut. Cras ultrices elit scelerisque augue imperdiet consectetur. Phasellus faucibus scelerisque pharetra.</p>"
        },
        {
            "title": "Article 8",
            "content": "<p>Lorem ipsum dolor sit amet, consectetur adipiscing elit. Pellentesque vestibulum tempus scelerisque. Morbi diam arcu, suscipit molestie rhoncus in, varius quis turpis. Quisque a risus eget leo cursus adipiscing in eu odio. Nullam id arcu mauris. In ullamcorper est et tortor vestibulum vitae rhoncus erat dignissim. Vestibulum dolor lorem, commodo ac sollicitudin sit amet, fermentum nec justo. Maecenas vitae interdum ipsum. Nulla facilisi. Ut eget nunc sed turpis sollicitudin varius tincidunt vel turpis. Sed blandit, sapien eu vehicula aliquam, metus neque rutrum massa, id vehicula elit lorem in sapien. Vestibulum a massa in sem posuere suscipit. Vivamus eget enim quis tellus mattis vehicula. Pellentesque rhoncus, massa in pellentesque scelerisque, mauris diam ultricies justo, vel vulputate metus lacus quis nibh. Mauris ut viverra sem.</p><p>Vivamus consectetur fringilla magna sed iaculis. Duis eros tortor, varius in tincidunt nec, ullamcorper non dolor. Suspendisse a turpis in sem laoreet molestie. Pellentesque consectetur suscipit dictum. Nam vehicula turpis nec massa laoreet rhoncus. Pellentesque in arcu orci. Aenean eget nulla metus. Sed magna massa, congue non rhoncus vitae, condimentum vitae nisi. Pellentesque a lectus nunc, quis elementum elit. Aliquam erat volutpat. Aliquam tincidunt sem quis elit blandit blandit. Nunc ultrices risus quis eros accumsan id luctus metus faucibus. Donec eu erat tortor, quis sagittis orci. Maecenas hendrerit enim id est pellentesque pulvinar. Aenean vulputate dapibus nibh vel sagittis.</p><p>In interdum magna ut mauris ultricies a dignissim massa feugiat. Suspendisse id lectus sit amet mi rhoncus tempor. Maecenas et facilisis metus. Suspendisse lorem neque, varius id dignissim a, egestas eget erat. Nulla congue volutpat eleifend. Quisque fringilla euismod mi, id malesuada augue rhoncus ut. Quisque viverra pharetra arcu, eget accumsan arcu adipiscing ut. Cras ultrices elit scelerisque augue imperdiet consectetur. Phasellus faucibus scelerisque pharetra.</p>"
        },
        {
            "title": "Article 9",
            "content": "<p>Lorem ipsum dolor sit amet, consectetur adipiscing elit. Pellentesque vestibulum tempus scelerisque. Morbi diam arcu, suscipit molestie rhoncus in, varius quis turpis. Quisque a risus eget leo cursus adipiscing in eu odio. Nullam id arcu mauris. In ullamcorper est et tortor vestibulum vitae rhoncus erat dignissim. Vestibulum dolor lorem, commodo ac sollicitudin sit amet, fermentum nec justo. Maecenas vitae interdum ipsum. Nulla facilisi. Ut eget nunc sed turpis sollicitudin varius tincidunt vel turpis. Sed blandit, sapien eu vehicula aliquam, metus neque rutrum massa, id vehicula elit lorem in sapien. Vestibulum a massa in sem posuere suscipit. Vivamus eget enim quis tellus mattis vehicula. Pellentesque rhoncus, massa in pellentesque scelerisque, mauris diam ultricies justo, vel vulputate metus lacus quis nibh. Mauris ut viverra sem.</p><p>Vivamus consectetur fringilla magna sed iaculis. Duis eros tortor, varius in tincidunt nec, ullamcorper non dolor. Suspendisse a turpis in sem laoreet molestie. Pellentesque consectetur suscipit dictum. Nam vehicula turpis nec massa laoreet rhoncus. Pellentesque in arcu orci. Aenean eget nulla metus. Sed magna massa, congue non rhoncus vitae, condimentum vitae nisi. Pellentesque a lectus nunc, quis elementum elit. Aliquam erat volutpat. Aliquam tincidunt sem quis elit blandit blandit. Nunc ultrices risus quis eros accumsan id luctus metus faucibus. Donec eu erat tortor, quis sagittis orci. Maecenas hendrerit enim id est pellentesque pulvinar. Aenean vulputate dapibus nibh vel sagittis.</p><p>In interdum magna ut mauris ultricies a dignissim massa feugiat. Suspendisse id lectus sit amet mi rhoncus tempor. Maecenas et facilisis metus. Suspendisse lorem neque, varius id dignissim a, egestas eget erat. Nulla congue volutpat eleifend. Quisque fringilla euismod mi, id malesuada augue rhoncus ut. Quisque viverra pharetra arcu, eget accumsan arcu adipiscing ut. Cras ultrices elit scelerisque augue imperdiet consectetur. Phasellus faucibus scelerisque pharetra.</p>"
        },
        {
            "title": "Article 10",
            "content": "<p>Lorem ipsum dolor sit amet, consectetur adipiscing elit. Pellentesque vestibulum tempus scelerisque. Morbi diam arcu, suscipit molestie rhoncus in, varius quis turpis. Quisque a risus eget leo cursus adipiscing in eu odio. Nullam id arcu mauris. In ullamcorper est et tortor vestibulum vitae rhoncus erat dignissim. Vestibulum dolor lorem, commodo ac sollicitudin sit amet, fermentum nec justo. Maecenas vitae interdum ipsum. Nulla facilisi. Ut eget nunc sed turpis sollicitudin varius tincidunt vel turpis. Sed blandit, sapien eu vehicula aliquam, metus neque rutrum massa, id vehicula elit lorem in sapien. Vestibulum a massa in sem posuere suscipit. Vivamus eget enim quis tellus mattis vehicula. Pellentesque rhoncus, massa in pellentesque scelerisque, mauris diam ultricies justo, vel vulputate metus lacus quis nibh. Mauris ut viverra sem.</p><p>Vivamus consectetur fringilla magna sed iaculis. Duis eros tortor, varius in tincidunt nec, ullamcorper non dolor. Suspendisse a turpis in sem laoreet molestie. Pellentesque consectetur suscipit dictum. Nam vehicula turpis nec massa laoreet rhoncus. Pellentesque in arcu orci. Aenean eget nulla metus. Sed magna massa, congue non rhoncus vitae, condimentum vitae nisi. Pellentesque a lectus nunc, quis elementum elit. Aliquam erat volutpat. Aliquam tincidunt sem quis elit blandit blandit. Nunc ultrices risus quis eros accumsan id luctus metus faucibus. Donec eu erat tortor, quis sagittis orci. Maecenas hendrerit enim id est pellentesque pulvinar. Aenean vulputate dapibus nibh vel sagittis.</p><p>In interdum magna ut mauris ultricies a dignissim massa feugiat. Suspendisse id lectus sit amet mi rhoncus tempor. Maecenas et facilisis metus. Suspendisse lorem neque, varius id dignissim a, egestas eget erat. Nulla congue volutpat eleifend. Quisque fringilla euismod mi, id malesuada augue rhoncus ut. Quisque viverra pharetra arcu, eget accumsan arcu adipiscing ut. Cras ultrices elit scelerisque augue imperdiet consectetur. Phasellus faucibus scelerisque pharetra.</p>"
        },
        {
            "title": "Article 11",
            "content": "<p>Lorem ipsum dolor sit amet, consectetur adipiscing elit. Pellentesque vestibulum tempus scelerisque. Morbi diam arcu, suscipit molestie rhoncus in, varius quis turpis. Quisque a risus eget leo cursus adipiscing in eu odio. Nullam id arcu mauris. In ullamcorper est et tortor vestibulum vitae rhoncus erat dignissim. Vestibulum dolor lorem, commodo ac sollicitudin sit amet, fermentum nec justo. Maecenas vitae interdum ipsum. Nulla facilisi. Ut eget nunc sed turpis sollicitudin varius tincidunt vel turpis. Sed blandit, sapien eu vehicula aliquam, metus neque rutrum massa, id vehicula elit lorem in sapien. Vestibulum a massa in sem posuere suscipit. Vivamus eget enim quis tellus mattis vehicula. Pellentesque rhoncus, massa in pellentesque scelerisque, mauris diam ultricies justo, vel vulputate metus lacus quis nibh. Mauris ut viverra sem.</p><p>Vivamus consectetur fringilla magna sed iaculis. Duis eros tortor, varius in tincidunt nec, ullamcorper non dolor. Suspendisse a turpis in sem laoreet molestie. Pellentesque consectetur suscipit dictum. Nam vehicula turpis nec massa laoreet rhoncus. Pellentesque in arcu orci. Aenean eget nulla metus. Sed magna massa, congue non rhoncus vitae, condimentum vitae nisi. Pellentesque a lectus nunc, quis elementum elit. Aliquam erat volutpat. Aliquam tincidunt sem quis elit blandit blandit. Nunc ultrices risus quis eros accumsan id luctus metus faucibus. Donec eu erat tortor, quis sagittis orci. Maecenas hendrerit enim id est pellentesque pulvinar. Aenean vulputate dapibus nibh vel sagittis.</p><p>In interdum magna ut mauris ultricies a dignissim massa feugiat. Suspendisse id lectus sit amet mi rhoncus tempor. Maecenas et facilisis metus. Suspendisse lorem neque, varius id dignissim a, egestas eget erat. Nulla congue volutpat eleifend. Quisque fringilla euismod mi, id malesuada augue rhoncus ut. Quisque viverra pharetra arcu, eget accumsan arcu adipiscing ut. Cras ultrices elit scelerisque augue imperdiet consectetur. Phasellus faucibus scelerisque pharetra.</p>"
        },
        {
            "title": "Article 12",
            "content": "<p>Lorem ipsum dolor sit amet, consectetur adipiscing elit. Pellentesque vestibulum tempus scelerisque. Morbi diam arcu, suscipit molestie rhoncus in, varius quis turpis. Quisque a risus eget leo cursus adipiscing in eu odio. Nullam id arcu mauris. In ullamcorper est et tortor vestibulum vitae rhoncus erat dignissim. Vestibulum dolor lorem, commodo ac sollicitudin sit amet, fermentum nec justo. Maecenas vitae interdum ipsum. Nulla facilisi. Ut eget nunc sed turpis sollicitudin varius tincidunt vel turpis. Sed blandit, sapien eu vehicula aliquam, metus neque rutrum massa, id vehicula elit lorem in sapien. Vestibulum a massa in sem posuere suscipit. Vivamus eget enim quis tellus mattis vehicula. Pellentesque rhoncus, massa in pellentesque scelerisque, mauris diam ultricies justo, vel vulputate metus lacus quis nibh. Mauris ut viverra sem.</p><p>Vivamus consectetur fringilla magna sed iaculis. Duis eros tortor, varius in tincidunt nec, ullamcorper non dolor. Suspendisse a turpis in sem laoreet molestie. Pellentesque consectetur suscipit dictum. Nam vehicula turpis nec massa laoreet rhoncus. Pellentesque in arcu orci. Aenean eget nulla metus. Sed magna massa, congue non rhoncus vitae, condimentum vitae nisi. Pellentesque a lectus nunc, quis elementum elit. Aliquam erat volutpat. Aliquam tincidunt sem quis elit blandit blandit. Nunc ultrices risus quis eros accumsan id luctus metus faucibus. Donec eu erat tortor, quis sagittis orci. Maecenas hendrerit enim id est pellentesque pulvinar. Aenean vulputate dapibus nibh vel sagittis.</p><p>In interdum magna ut mauris ultricies a dignissim massa feugiat. Suspendisse id lectus sit amet mi rhoncus tempor. Maecenas et facilisis metus. Suspendisse lorem neque, varius id dignissim a, egestas eget erat. Nulla congue volutpat eleifend. Quisque fringilla euismod mi, id malesuada augue rhoncus ut. Quisque viverra pharetra arcu, eget accumsan arcu adipiscing ut. Cras ultrices elit scelerisque augue imperdiet consectetur. Phasellus faucibus scelerisque pharetra.</p>"
        },
        {
            "title": "Article 13",
            "content": "<p>Lorem ipsum dolor sit amet, consectetur adipiscing elit. Pellentesque vestibulum tempus scelerisque. Morbi diam arcu, suscipit molestie rhoncus in, varius quis turpis. Quisque a risus eget leo cursus adipiscing in eu odio. Nullam id arcu mauris. In ullamcorper est et tortor vestibulum vitae rhoncus erat dignissim. Vestibulum dolor lorem, commodo ac sollicitudin sit amet, fermentum nec justo. Maecenas vitae interdum ipsum. Nulla facilisi. Ut eget nunc sed turpis sollicitudin varius tincidunt vel turpis. Sed blandit, sapien eu vehicula aliquam, metus neque rutrum massa, id vehicula elit lorem in sapien. Vestibulum a massa in sem posuere suscipit. Vivamus eget enim quis tellus mattis vehicula. Pellentesque rhoncus, massa in pellentesque scelerisque, mauris diam ultricies justo, vel vulputate metus lacus quis nibh. Mauris ut viverra sem.</p><p>Vivamus consectetur fringilla magna sed iaculis. Duis eros tortor, varius in tincidunt nec, ullamcorper non dolor. Suspendisse a turpis in sem laoreet molestie. Pellentesque consectetur suscipit dictum. Nam vehicula turpis nec massa laoreet rhoncus. Pellentesque in arcu orci. Aenean eget nulla metus. Sed magna massa, congue non rhoncus vitae, condimentum vitae nisi. Pellentesque a lectus nunc, quis elementum elit. Aliquam erat volutpat. Aliquam tincidunt sem quis elit blandit blandit. Nunc ultrices risus quis eros accumsan id luctus metus faucibus. Donec eu erat tortor, quis sagittis orci. Maecenas hendrerit enim id est pellentesque pulvinar. Aenean vulputate dapibus nibh vel sagittis.</p><p>In interdum magna ut mauris ultricies a dignissim massa feugiat. Suspendisse id lectus sit amet mi rhoncus tempor. Maecenas et facilisis metus. Suspendisse lorem neque, varius id dignissim a, egestas eget erat. Nulla congue volutpat eleifend. Quisque fringilla euismod mi, id malesuada augue rhoncus ut. Quisque viverra pharetra arcu, eget accumsan arcu adipiscing ut. Cras ultrices elit scelerisque augue imperdiet consectetur. Phasellus faucibus scelerisque pharetra.</p>"
        },
        {
            "title": "Article 14",
            "content": "<p>Lorem ipsum dolor sit amet, consectetur adipiscing elit. Pellentesque vestibulum tempus scelerisque. Morbi diam arcu, suscipit molestie rhoncus in, varius quis turpis. Quisque a risus eget leo cursus adipiscing in eu odio. Nullam id arcu mauris. In ullamcorper est et tortor vestibulum vitae rhoncus erat dignissim. Vestibulum dolor lorem, commodo ac sollicitudin sit amet, fermentum nec justo. Maecenas vitae interdum ipsum. Nulla facilisi. Ut eget nunc sed turpis sollicitudin varius tincidunt vel turpis. Sed blandit, sapien eu vehicula aliquam, metus neque rutrum massa, id vehicula elit lorem in sapien. Vestibulum a massa in sem posuere suscipit. Vivamus eget enim quis tellus mattis vehicula. Pellentesque rhoncus, massa in pellentesque scelerisque, mauris diam ultricies justo, vel vulputate metus lacus quis nibh. Mauris ut viverra sem.</p><p>Vivamus consectetur fringilla magna sed iaculis. Duis eros tortor, varius in tincidunt nec, ullamcorper non dolor. Suspendisse a turpis in sem laoreet molestie. Pellentesque consectetur suscipit dictum. Nam vehicula turpis nec massa laoreet rhoncus. Pellentesque in arcu orci. Aenean eget nulla metus. Sed magna massa, congue non rhoncus vitae, condimentum vitae nisi. Pellentesque a lectus nunc, quis elementum elit. Aliquam erat volutpat. Aliquam tincidunt sem quis elit blandit blandit. Nunc ultrices risus quis eros accumsan id luctus metus faucibus. Donec eu erat tortor, quis sagittis orci. Maecenas hendrerit enim id est pellentesque pulvinar. Aenean vulputate dapibus nibh vel sagittis.</p><p>In interdum magna ut mauris ultricies a dignissim massa feugiat. Suspendisse id lectus sit amet mi rhoncus tempor. Maecenas et facilisis metus. Suspendisse lorem neque, varius id dignissim a, egestas eget erat. Nulla congue volutpat eleifend. Quisque fringilla euismod mi, id malesuada augue rhoncus ut. Quisque viverra pharetra arcu, eget accumsan arcu adipiscing ut. Cras ultrices elit scelerisque augue imperdiet consectetur. Phasellus faucibus scelerisque pharetra.</p>"
        },
        {
            "title": "Article 15",
            "content": "<p>Lorem ipsum dolor sit amet, consectetur adipiscing elit. Pellentesque vestibulum tempus scelerisque. Morbi diam arcu, suscipit molestie rhoncus in, varius quis turpis. Quisque a risus eget leo cursus adipiscing in eu odio. Nullam id arcu mauris. In ullamcorper est et tortor vestibulum vitae rhoncus erat dignissim. Vestibulum dolor lorem, commodo ac sollicitudin sit amet, fermentum nec justo. Maecenas vitae interdum ipsum. Nulla facilisi. Ut eget nunc sed turpis sollicitudin varius tincidunt vel turpis. Sed blandit, sapien eu vehicula aliquam, metus neque rutrum massa, id vehicula elit lorem in sapien. Vestibulum a massa in sem posuere suscipit. Vivamus eget enim quis tellus mattis vehicula. Pellentesque rhoncus, massa in pellentesque scelerisque, mauris diam ultricies justo, vel vulputate metus lacus quis nibh. Mauris ut viverra sem.</p><p>Vivamus consectetur fringilla magna sed iaculis. Duis eros tortor, varius in tincidunt nec, ullamcorper non dolor. Suspendisse a turpis in sem laoreet molestie. Pellentesque consectetur suscipit dictum. Nam vehicula turpis nec massa laoreet rhoncus. Pellentesque in arcu orci. Aenean eget nulla metus. Sed magna massa, congue non rhoncus vitae, condimentum vitae nisi. Pellentesque a lectus nunc, quis elementum elit. Aliquam erat volutpat. Aliquam tincidunt sem quis elit blandit blandit. Nunc ultrices risus quis eros accumsan id luctus metus faucibus. Donec eu erat tortor, quis sagittis orci. Maecenas hendrerit enim id est pellentesque pulvinar. Aenean vulputate dapibus nibh vel sagittis.</p><p>In interdum magna ut mauris ultricies a dignissim massa feugiat. Suspendisse id lectus sit amet mi rhoncus tempor. Maecenas et facilisis metus. Suspendisse lorem neque, varius id dignissim a, egestas eget erat. Nulla congue volutpat eleifend. Quisque fringilla euismod mi, id malesuada augue rhoncus ut. Quisque viverra pharetra arcu, eget accumsan arcu adipiscing ut. Cras ultrices elit scelerisque augue imperdiet consectetur. Phasellus faucibus scelerisque pharetra.</p>"
        },
        {
            "title": "Article 16",
            "content": "<p>Lorem ipsum dolor sit amet, consectetur adipiscing elit. Pellentesque vestibulum tempus scelerisque. Morbi diam arcu, suscipit molestie rhoncus in, varius quis turpis. Quisque a risus eget leo cursus adipiscing in eu odio. Nullam id arcu mauris. In ullamcorper est et tortor vestibulum vitae rhoncus erat dignissim. Vestibulum dolor lorem, commodo ac sollicitudin sit amet, fermentum nec justo. Maecenas vitae interdum ipsum. Nulla facilisi. Ut eget nunc sed turpis sollicitudin varius tincidunt vel turpis. Sed blandit, sapien eu vehicula aliquam, metus neque rutrum massa, id vehicula elit lorem in sapien. Vestibulum a massa in sem posuere suscipit. Vivamus eget enim quis tellus mattis vehicula. Pellentesque rhoncus, massa in pellentesque scelerisque, mauris diam ultricies justo, vel vulputate metus lacus quis nibh. Mauris ut viverra sem.</p><p>Vivamus consectetur fringilla magna sed iaculis. Duis eros tortor, varius in tincidunt nec, ullamcorper non dolor. Suspendisse a turpis in sem laoreet molestie. Pellentesque consectetur suscipit dictum. Nam vehicula turpis nec massa laoreet rhoncus. Pellentesque in arcu orci. Aenean eget nulla metus. Sed magna massa, congue non rhoncus vitae, condimentum vitae nisi. Pellentesque a lectus nunc, quis elementum elit. Aliquam erat volutpat. Aliquam tincidunt sem quis elit blandit blandit. Nunc ultrices risus quis eros accumsan id luctus metus faucibus. Donec eu erat tortor, quis sagittis orci. Maecenas hendrerit enim id est pellentesque pulvinar. Aenean vulputate dapibus nibh vel sagittis.</p><p>In interdum magna ut mauris ultricies a dignissim massa feugiat. Suspendisse id lectus sit amet mi rhoncus tempor. Maecenas et facilisis metus. Suspendisse lorem neque, varius id dignissim a, egestas eget erat. Nulla congue volutpat eleifend. Quisque fringilla euismod mi, id malesuada augue rhoncus ut. Quisque viverra pharetra arcu, eget accumsan arcu adipiscing ut. Cras ultrices elit scelerisque augue imperdiet consectetur. Phasellus faucibus scelerisque pharetra.</p>"
        },
        {
            "title": "Article 17",
            "content": "<p>Lorem ipsum dolor sit amet, consectetur adipiscing elit. Pellentesque vestibulum tempus scelerisque. Morbi diam arcu, suscipit molestie rhoncus in, varius quis turpis. Quisque a risus eget leo cursus adipiscing in eu odio. Nullam id arcu mauris. In ullamcorper est et tortor vestibulum vitae rhoncus erat dignissim. Vestibulum dolor lorem, commodo ac sollicitudin sit amet, fermentum nec justo. Maecenas vitae interdum ipsum. Nulla facilisi. Ut eget nunc sed turpis sollicitudin varius tincidunt vel turpis. Sed blandit, sapien eu vehicula aliquam, metus neque rutrum massa, id vehicula elit lorem in sapien. Vestibulum a massa in sem posuere suscipit. Vivamus eget enim quis tellus mattis vehicula. Pellentesque rhoncus, massa in pellentesque scelerisque, mauris diam ultricies justo, vel vulputate metus lacus quis nibh. Mauris ut viverra sem.</p><p>Vivamus consectetur fringilla magna sed iaculis. Duis eros tortor, varius in tincidunt nec, ullamcorper non dolor. Suspendisse a turpis in sem laoreet molestie. Pellentesque consectetur suscipit dictum. Nam vehicula turpis nec massa laoreet rhoncus. Pellentesque in arcu orci. Aenean eget nulla metus. Sed magna massa, congue non rhoncus vitae, condimentum vitae nisi. Pellentesque a lectus nunc, quis elementum elit. Aliquam erat volutpat. Aliquam tincidunt sem quis elit blandit blandit. Nunc ultrices risus quis eros accumsan id luctus metus faucibus. Donec eu erat tortor, quis sagittis orci. Maecenas hendrerit enim id est pellentesque pulvinar. Aenean vulputate dapibus nibh vel sagittis.</p><p>In interdum magna ut mauris ultricies a dignissim massa feugiat. Suspendisse id lectus sit amet mi rhoncus tempor. Maecenas et facilisis metus. Suspendisse lorem neque, varius id dignissim a, egestas eget erat. Nulla congue volutpat eleifend. Quisque fringilla euismod mi, id malesuada augue rhoncus ut. Quisque viverra pharetra arcu, eget accumsan arcu adipiscing ut. Cras ultrices elit scelerisque augue imperdiet consectetur. Phasellus faucibus scelerisque pharetra.</p>"
        },
        {
            "title": "Article 18",
            "content": "<p>Lorem ipsum dolor sit amet, consectetur adipiscing elit. Pellentesque vestibulum tempus scelerisque. Morbi diam arcu, suscipit molestie rhoncus in, varius quis turpis. Quisque a risus eget leo cursus adipiscing in eu odio. Nullam id arcu mauris. In ullamcorper est et tortor vestibulum vitae rhoncus erat dignissim. Vestibulum dolor lorem, commodo ac sollicitudin sit amet, fermentum nec justo. Maecenas vitae interdum ipsum. Nulla facilisi. Ut eget nunc sed turpis sollicitudin varius tincidunt vel turpis. Sed blandit, sapien eu vehicula aliquam, metus neque rutrum massa, id vehicula elit lorem in sapien. Vestibulum a massa in sem posuere suscipit. Vivamus eget enim quis tellus mattis vehicula. Pellentesque rhoncus, massa in pellentesque scelerisque, mauris diam ultricies justo, vel vulputate metus lacus quis nibh. Mauris ut viverra sem.</p><p>Vivamus consectetur fringilla magna sed iaculis. Duis eros tortor, varius in tincidunt nec, ullamcorper non dolor. Suspendisse a turpis in sem laoreet molestie. Pellentesque consectetur suscipit dictum. Nam vehicula turpis nec massa laoreet rhoncus. Pellentesque in arcu orci. Aenean eget nulla metus. Sed magna massa, congue non rhoncus vitae, condimentum vitae nisi. Pellentesque a lectus nunc, quis elementum elit. Aliquam erat volutpat. Aliquam tincidunt sem quis elit blandit blandit. Nunc ultrices risus quis eros accumsan id luctus metus faucibus. Donec eu erat tortor, quis sagittis orci. Maecenas hendrerit enim id est pellentesque pulvinar. Aenean vulputate dapibus nibh vel sagittis.</p><p>In interdum magna ut mauris ultricies a dignissim massa feugiat. Suspendisse id lectus sit amet mi rhoncus tempor. Maecenas et facilisis metus. Suspendisse lorem neque, varius id dignissim a, egestas eget erat. Nulla congue volutpat eleifend. Quisque fringilla euismod mi, id malesuada augue rhoncus ut. Quisque viverra pharetra arcu, eget accumsan arcu adipiscing ut. Cras ultrices elit scelerisque augue imperdiet consectetur. Phasellus faucibus scelerisque pharetra.</p>"
        },
        {
            "title": "Article 19",
            "content": "<p>Lorem ipsum dolor sit amet, consectetur adipiscing elit. Pellentesque vestibulum tempus scelerisque. Morbi diam arcu, suscipit molestie rhoncus in, varius quis turpis. Quisque a risus eget leo cursus adipiscing in eu odio. Nullam id arcu mauris. In ullamcorper est et tortor vestibulum vitae rhoncus erat dignissim. Vestibulum dolor lorem, commodo ac sollicitudin sit amet, fermentum nec justo. Maecenas vitae interdum ipsum. Nulla facilisi. Ut eget nunc sed turpis sollicitudin varius tincidunt vel turpis. Sed blandit, sapien eu vehicula aliquam, metus neque rutrum massa, id vehicula elit lorem in sapien. Vestibulum a massa in sem posuere suscipit. Vivamus eget enim quis tellus mattis vehicula. Pellentesque rhoncus, massa in pellentesque scelerisque, mauris diam ultricies justo, vel vulputate metus lacus quis nibh. Mauris ut viverra sem.</p><p>Vivamus consectetur fringilla magna sed iaculis. Duis eros tortor, varius in tincidunt nec, ullamcorper non dolor. Suspendisse a turpis in sem laoreet molestie. Pellentesque consectetur suscipit dictum. Nam vehicula turpis nec massa laoreet rhoncus. Pellentesque in arcu orci. Aenean eget nulla metus. Sed magna massa, congue non rhoncus vitae, condimentum vitae nisi. Pellentesque a lectus nunc, quis elementum elit. Aliquam erat volutpat. Aliquam tincidunt sem quis elit blandit blandit. Nunc ultrices risus quis eros accumsan id luctus metus faucibus. Donec eu erat tortor, quis sagittis orci. Maecenas hendrerit enim id est pellentesque pulvinar. Aenean vulputate dapibus nibh vel sagittis.</p><p>In interdum magna ut mauris ultricies a dignissim massa feugiat. Suspendisse id lectus sit amet mi rhoncus tempor. Maecenas et facilisis metus. Suspendisse lorem neque, varius id dignissim a, egestas eget erat. Nulla congue volutpat eleifend. Quisque fringilla euismod mi, id malesuada augue rhoncus ut. Quisque viverra pharetra arcu, eget accumsan arcu adipiscing ut. Cras ultrices elit scelerisque augue imperdiet consectetur. Phasellus faucibus scelerisque pharetra.</p>"
        }
    ]
}
